README.rst
setup.py
sniper/__init__.py
sniper/app.py
sniper/authentications.py
sniper/controllers.py
sniper/exceptions.py
sniper/filters.py
sniper/http.py
sniper/middlewares.py
sniper/models.py
sniper/parsers.py
sniper/requests.py
sniper/responses.py
sniper/sessions.py
sniper/tests.py
sniper/utils.py
sniper.egg-info/PKG-INFO
sniper.egg-info/SOURCES.txt
sniper.egg-info/dependency_links.txt
sniper.egg-info/top_level.txt
sniper/url/__init__.py
sniper/url/actions.py
sniper/url/patterns.py
sniper/url/resolvers.py