Metadata-Version: 1.1
Name: sniper
Version: 0.0.6
Summary: an asynchronous restful web framework base on asyncio
Home-page: https://github.com/lexdene/py-sniper
Author: Elephant Liu
Author-email: lexdene@gmail.com
License: GPLv3
Platform: any
Classifier: Development Status :: 3 - Alpha
Classifier: Environment :: Web Environment
Classifier: Intended Audience :: Developers
Classifier: License :: OSI Approved :: GNU General Public License v3 (GPLv3)
Classifier: Operating System :: OS Independent
Classifier: Programming Language :: Python
Classifier: Programming Language :: Python :: 3.5
Classifier: Programming Language :: Python :: 3.6
Classifier: Topic :: Internet :: WWW/HTTP
